odoo/addons/l10n_br_stock/README.rst
odoo/addons/l10n_br_stock/__init__.py
odoo/addons/l10n_br_stock/__manifest__.py
odoo/addons/l10n_br_stock/hooks.py
odoo/addons/l10n_br_stock/demo/res_company_demo.xml
odoo/addons/l10n_br_stock/demo/res_users_demo.xml
odoo/addons/l10n_br_stock/demo/stock_inventory_demo.xml
odoo/addons/l10n_br_stock/demo/stock_location_demo.xml
odoo/addons/l10n_br_stock/i18n/l10n_br_stock.pot
odoo/addons/l10n_br_stock/i18n/pt_BR.po
odoo/addons/l10n_br_stock/models/__init__.py
odoo/addons/l10n_br_stock/models/stock_picking.py
odoo/addons/l10n_br_stock/readme/CONFIGURE.rst
odoo/addons/l10n_br_stock/readme/CONTRIBUTORS.rst
odoo/addons/l10n_br_stock/readme/DESCRIPTION.rst
odoo/addons/l10n_br_stock/readme/HISTORY.rst
odoo/addons/l10n_br_stock/readme/INSTALL.rst
odoo/addons/l10n_br_stock/readme/USAGE.rst
odoo/addons/l10n_br_stock/static/description/icon.png
odoo/addons/l10n_br_stock/static/description/index.html
odoo/addons/l10n_br_stock/views/stock_picking_view.xml
odoo14_addon_l10n_br_stock-14.0.2.1.3.dist-info/METADATA
odoo14_addon_l10n_br_stock-14.0.2.1.3.dist-info/WHEEL
odoo14_addon_l10n_br_stock-14.0.2.1.3.dist-info/top_level.txt
odoo14_addon_l10n_br_stock-14.0.2.1.3.dist-info/RECORD
